README.md
setup.cfg
setup.py
src/qollib/__init__.py
src/qollib.egg-info/PKG-INFO
src/qollib.egg-info/SOURCES.txt
src/qollib.egg-info/dependency_links.txt
src/qollib.egg-info/requires.txt
src/qollib.egg-info/top_level.txt
src/qollib/collections/__init__.py
src/qollib/collections/chunking.py
src/qollib/collections/reducing.py
src/qollib/processing/__init__.py
src/qollib/processing/execution.py
src/qollib/processing/testing.py
src/qollib/processing/thread.py
src/qollib/strings/__init__.py
src/qollib/strings/np_shape_parser.py
src/qollib/strings/numeric.py
src/qollib/ui/__init__.py
src/qollib/ui/log.py
src/qollib/ui/progress.py