Metadata-Version: 2.1
Name: qollib
Version: 0.1.3
Summary: Quality of Life tools library.
Home-page: https://gitlab.gwdg.de/hoelken/qollib
Author: Johannes Hölken
Author-email: hoelken@mps.mpg.de
Project-URL: Bug Tracker, https://gitlab.gwdg.de/hoelken/qollib/issues
Classifier: Programming Language :: Python :: 3
Classifier: License :: OSI Approved :: BSD License
Classifier: Operating System :: OS Independent
Requires-Python: >=3.8
Requires-Dist: numpy>=1.23
